cafe/__init__.py
cafe/data_transform.py
cafe/ml.py
cafe-2.0.0.dist-info/LICENSE
cafe-2.0.0.dist-info/METADATA
cafe-2.0.0.dist-info/WHEEL
cafe-2.0.0.dist-info/top_level.txt
cafe-2.0.0.dist-info/RECORD
