Metadata-Version: 2.1
Name: cafe
Version: 2.0.0
Summary: Classifying Antibodies for Expression
Home-page: https://github.com/lin-justin/cafe
Author: Justin Lin
License: UNKNOWN
Platform: UNKNOWN
Classifier: License :: OSI Approved :: MIT License
Classifier: Intended Audience :: Science/Research
Classifier: Operating System :: OS Independent
Classifier: Programming Language :: Python
Classifier: Programming Language :: Python :: 3
Classifier: Programming Language :: Python :: 3.7
Requires-Python: >=3.7
Requires-Dist: biopython (>=1.73)
Requires-Dist: matplotlib (>=3.1.2)
Requires-Dist: numpy (>=1.17.4)
Requires-Dist: pandas (>=0.24.2)
Requires-Dist: scikit-learn (==0.22)
Requires-Dist: scikit-plot (==0.3.7)
Requires-Dist: seaborn (==0.9.0)
Requires-Dist: imbalanced-learn (==0.6.1)
Requires-Dist: eli5 (==0.10.1)
